{
  "project_info": {
    "project_number": "575796114988",
    "firebase_url": "https://software-project-4ae0c.firebaseio.com",
    "project_id": "software-project-4ae0c",
    "storage_bucket": "software-project-4ae0c.appspot.com"
  },
  "client": [
    {
      "client_info": {
        "mobilesdk_app_id": "1:575796114988:android:a6bbe4984e1f0ecc",
        "android_client_info": {
          "package_name": "com.example.liam.softwareproject"
        }
      },
      "oauth_client": [
        {
          "client_id": "575796114988-9ae5n935d14oar6oikb1q87bjbf209a4.apps.googleusercontent.com",
          "client_type": 3
        },
        {
          "client_id": "575796114988-9ae5n935d14oar6oikb1q87bjbf209a4.apps.googleusercontent.com",
          "client_type": 3
        }
      ],
      "api_key": [
        {
          "current_key": "AIzaSyC74i6rHOBHos64OjbpFHH5b_0LZBS1gWg"
        }
      ],
      "services": {
        "analytics_service": {
          "status": 1
        },
        "appinvite_service": {
          "status": 1,
          "other_platform_oauth_client": []
        },
        "ads_service": {
          "status": 2
        }
      }
    }
  ],
  "configuration_version": "1"
}